impyrial/__init__.py
impyrial/utils.py
impyrial/length/__init__.py
impyrial/length/api.py
impyrial/length/core.py
impyrial/weight/__init__.py
impyrial/weight/api.py
impyrial/weight/core.py
impyrial_akhedkar_talentumglobal-0.2.0.dist-info/LICENSE.txt
impyrial_akhedkar_talentumglobal-0.2.0.dist-info/METADATA
impyrial_akhedkar_talentumglobal-0.2.0.dist-info/WHEEL
impyrial_akhedkar_talentumglobal-0.2.0.dist-info/top_level.txt
impyrial_akhedkar_talentumglobal-0.2.0.dist-info/RECORD
